Dividender/Dividender.py
Dividender/main.py
DividenderX-0.0.5.dist-info/METADATA
DividenderX-0.0.5.dist-info/WHEEL
DividenderX-0.0.5.dist-info/top_level.txt
DividenderX-0.0.5.dist-info/RECORD
