Metadata-Version: 2.1
Name: DividenderX
Version: 0.0.5
Summary: Gives you a close estimate of how much your dividend payer asset will grow overtime. 
Author: Xavier Navarro
License: UNKNOWN
Platform: UNKNOWN
Classifier: Programming Language :: Python :: 3
Classifier: Programming Language :: Python :: 3.6
Classifier: Programming Language :: Python :: 3.7
Classifier: License :: OSI Approved :: GNU General Public License v2 or later (GPLv2+)
Classifier: Operating System :: OS Independent
